email_pydantic/__init__.py
email_pydantic/client.py
email_pydantic/constans.py
email_pydantic/email_processing.py
email_pydantic/email_responder.py
email_pydantic/exception.py
email_pydantic/helpers.py
email_pydantic/structs.py
email_pydantic-0.1.0.dist-info/entry_points.txt
email_pydantic-0.1.0.dist-info/WHEEL
email_pydantic-0.1.0.dist-info/METADATA
email_pydantic-0.1.0.dist-info/RECORD
