Metadata-Version: 2.1
Name: email-pydantic
Version: 0.1.0
Summary: 
Home-page: https://github.com/MattiooFR/package_name
License: MIT
Keywords: keyword,another_keyword
Author: alexander.mescheryakov
Author-email: .mescheryakov@semrush.com
Requires-Python: >=3.10,<4.0
Classifier: License :: OSI Approved :: MIT License
Classifier: Programming Language :: Python :: 3
Classifier: Programming Language :: Python :: 3.10
Requires-Dist: DateTime (>=4.7,<5.0)
Requires-Dist: IMAPClient (>=2.3.1,<3.0.0)
Requires-Dist: email-validator (>=1.3.0,<2.0.0)
Requires-Dist: html2text (>=2020.1.16,<2021.0.0)
Requires-Dist: pydantic (>=1.10.2,<2.0.0)
Requires-Dist: pytz (>=2022.6,<2023.0)
Requires-Dist: zope.interface (>=5.5.2,<6.0.0)
Project-URL: Repository, https://github.com/MattiooFR/package_name
